pbrequest/__init__.py
pbrequest/common.py
pbrequest/deletion.py
pbrequest/download.py
pbrequest/exceptions.py
pbrequest/upload.py
pbrequest-1.0.1.dist-info/LICENSE
pbrequest-1.0.1.dist-info/METADATA
pbrequest-1.0.1.dist-info/WHEEL
pbrequest-1.0.1.dist-info/top_level.txt
pbrequest-1.0.1.dist-info/RECORD
