Metadata-Version: 2.1
Name: pbrequest
Version: 1.0.1
Summary: PrivateBin Request + customer http headers
Home-page: https://github.com/vietvq/privatebin-request
Author: vietvo
Author-email: Viet <viqivi@gmail.com>
Project-URL: Homepage, https://github.com/vietvq/privatebin-request
Project-URL: Issues, https://github.com/vietvq/privatebin-request/issues
Classifier: License :: OSI Approved :: MIT License
Classifier: Operating System :: OS Independent
Classifier: Programming Language :: Python :: 3
Classifier: Programming Language :: Python :: 3.6
Classifier: Programming Language :: Python :: 3.7
Classifier: Programming Language :: Python :: 3.8
Classifier: Programming Language :: Python :: 3.9
Classifier: Topic :: Security :: Cryptography
Requires-Python: >=3.6
License-File: LICENSE
